[
    {
        "Id": "a82c5c90-501e-11e7-84f2-f1c53e5d94d8",
        "Rule": 8,
        "SellerId": 1,
        "Name": "TEST DB123456",
        "BaseReference": 1,
        "State": 16,
        "Reference": "Händlerpreis",
        "Percent": 10,
        "AbsoluteValue": -1,
        "ebayListerLinkedArticles": 6,
        "amazonListerLinkedArticles": 3,
        "runningEbayItems": 2
    },
    {
        "Id": "a82cd1c0-501e-11e7-84f2-f1c53e5d94d8",
        "Rule": 5,
        "SellerId": 1,
        "Name": "Testregel",
        "BaseReference": 1,
        "State": 18,
        "Reference": "Verkaufspreis",
        "Percent": 3,
        "AbsoluteValue": 0,
        "ebayListerLinkedArticles": 1,
        "amazonListerLinkedArticles": 5,
        "runningEbayItems": 0
    },
    {
        "Id": "a82d1fe0-501e-11e7-84f2-f1c53e5d94d8",
        "Rule": 3,
        "SellerId": 1,
        "Name": "Amazon 10%",
        "BaseReference": 1,
        "State": 33,
        "Reference": "Einkaufspreis",
        "Percent": 3,
        "AbsoluteValue": 3,
        "ebayListerLinkedArticles": 0,
        "amazonListerLinkedArticles": 18,
        "runningEbayItems": 0
    },
    {
        "Id": "a82de330-501e-11e7-84f2-f1c53e5d94d8",
        "Rule": 9,
        "SellerId": 1,
        "Name": "LukasTest2",
        "BaseReference": 1,
        "State": 22,
        "Reference": "Einkaufspreis",
        "Percent": 10,
        "AbsoluteValue": -101,
        "ebayListerLinkedArticles": 15,
        "amazonListerLinkedArticles": 22,
        "runningEbayItems": 4
    },
    {
        "Id": "a82e3150-501e-11e7-84f2-f1c53e5d94d8",
        "Rule": 15,
        "SellerId": 1,
        "Name": "mk_negativ_werte",
        "BaseReference": 1,
        "State": 14,
        "Reference": "Verkaufspreis",
        "Percent": 50,
        "AbsoluteValue": 0,
        "ebayListerLinkedArticles": 2,
        "amazonListerLinkedArticles": 2,
        "runningEbayItems": 1
    },
    {
        "Id": "a82ef4a0-501e-11e7-84f2-f1c53e5d94d8",
        "Rule": 17,
        "SellerId": 1,
        "Name": "Test Olaf Prozent auf VK",
        "BaseReference": 1,
        "State": 11,
        "Reference": "Verkaufspreis",
        "Percent": 18,
        "AbsoluteValue": -15.4,
        "ebayListerLinkedArticles": 0,
        "amazonListerLinkedArticles": 0,
        "runningEbayItems": 0
    },
    {
        "Id": "f4dacb30-501e-11e7-8d85-350d92152cbe",
        "Rule": 9,
        "SellerId": 1,
        "Name": "LukasTest2",
        "BaseReference": 1,
        "State": 22,
        "Reference": "Händlerpreis",
        "Percent": 10,
        "AbsoluteValue": -101,
        "ebayListerLinkedArticles": 4,
        "amazonListerLinkedArticles": 56,
        "runningEbayItems": 1
    },
    {
        "Id": "a8300610-501e-11e7-84f2-f1c53e5d94d8",
        "Rule": 48,
        "SellerId": 1,
        "Name": "LukasTestDynPreis",
        "BaseReference": 1,
        "State": 22,
        "Reference": "Verkaufspreis",
        "Percent": -15,
        "AbsoluteValue": -1.5,
        "ebayListerLinkedArticles": 7,
        "amazonListerLinkedArticles": 8,
        "runningEbayItems": 4
    },
    {
        "Id": "a8305430-501e-11e7-84f2-f1c53e5d94d8",
        "Rule": 18,
        "SellerId": 1,
        "Name": "Testregel 15",
        "BaseReference": 1,
        "State": 48,
        "Reference": "Einkaufspreis",
        "Percent": 1051,
        "AbsoluteValue": 305,
        "ebayListerLinkedArticles": 19,
        "amazonListerLinkedArticles": 89,
        "runningEbayItems": 15
    },
    {
        "Id": "f4d9b9c0-501e-11e7-8d85-350d92152cbe",
        "Rule": 19,
        "SellerId": 1,
        "Name": "Testregel 42",
        "BaseReference": 1,
        "State": 42,
        "Reference": "Einkaufspreis",
        "Percent": -157,
        "AbsoluteValue": -0.5,
        "ebayListerLinkedArticles": 24,
        "amazonListerLinkedArticles": 17,
        "runningEbayItems": 0
    },
    {
        "Id": "a8318cb0-501e-11e7-84f2-f1c53e5d94d8",
        "Rule": 23,
        "SellerId": 1,
        "Name": "Testregel 23",
        "BaseReference": 1,
        "State": 15,
        "Reference": "Händlerpreis",
        "Percent": 15,
        "AbsoluteValue": 15,
        "ebayListerLinkedArticles": 0,
        "amazonListerLinkedArticles": 3,
        "runningEbayItems": 0
    }
]